unitstools/__init__.py
unitstools/unitstools.py
unitstools-0.1.2.dist-info/LICENSE
unitstools-0.1.2.dist-info/WHEEL
unitstools-0.1.2.dist-info/METADATA
unitstools-0.1.2.dist-info/RECORD
