Metadata-Version: 2.1
Name: unitstools
Version: 0.1.2
Summary: Unitstools is a Python library that helps to manage units of measurement in code via static typing.
Home-page: https://github.com/AloizioMacedo/unitstools
Author: Aloizio Macedo
Author-email: aloiziomacedo@gmail.com
Requires-Python: >=3.7,<4.0
Classifier: Programming Language :: Python :: 3
Classifier: Programming Language :: Python :: 3.7
Classifier: Programming Language :: Python :: 3.8
Classifier: Programming Language :: Python :: 3.9
Classifier: Programming Language :: Python :: 3.10
Project-URL: Documentation, https://unitstools.readthedocs.io/
Project-URL: Repository, https://github.com/AloizioMacedo/unitstools
